pyavrio/__init__.py
pyavrio/_version.py
pyavrio/auth.py
pyavrio/avrio_rest_handler.py
pyavrio/client.py
pyavrio/constants.py
pyavrio/dbapi.py
pyavrio/endpoints.py
pyavrio/exceptions.py
pyavrio/logging.py
pyavrio/pyavrio_functions.py
pyavrio/query_parser.py
pyavrio/transaction.py
pyavrio/sqlalchemy/__init__.py
pyavrio/sqlalchemy/compiler.py
pyavrio/sqlalchemy/datatype.py
pyavrio/sqlalchemy/dialect.py
pyavrio/sqlalchemy/error.py
pyavrio/sqlalchemy/util.py
pyavrio-20.0.3.dist-info/METADATA
pyavrio-20.0.3.dist-info/WHEEL
pyavrio-20.0.3.dist-info/entry_points.txt
pyavrio-20.0.3.dist-info/top_level.txt
pyavrio-20.0.3.dist-info/RECORD
